clickup_mcp/__init__.py
clickup_mcp/__main__.py
clickup_mcp/client.py
clickup_mcp/entry.py
clickup_mcp/exceptions.py
clickup_mcp/utils.py
clickup_mcp/_base/__init__.py
clickup_mcp/_base/app.py
clickup_mcp/api/__init__.py
clickup_mcp/api/space.py
clickup_mcp/api/team.py
clickup_mcp/mcp_server/__init__.py
clickup_mcp/mcp_server/app.py
clickup_mcp/mcp_server/space.py
clickup_mcp/mcp_server/team.py
clickup_mcp/models/__init__.py
clickup_mcp/models/cli.py
clickup_mcp/models/domain/__init__.py
clickup_mcp/models/domain/base.py
clickup_mcp/models/domain/space.py
clickup_mcp/models/domain/team.py
clickup_mcp/models/dto/__init__.py
clickup_mcp/models/dto/base.py
clickup_mcp/models/dto/health_check.py
clickup_mcp/web_server/__init__.py
clickup_mcp/web_server/app.py
clickup_mcp_server-0.0.8.dist-info/METADATA
clickup_mcp_server-0.0.8.dist-info/WHEEL
clickup_mcp_server-0.0.8.dist-info/entry_points.txt
clickup_mcp_server-0.0.8.dist-info/licenses/LICENSE
clickup_mcp_server-0.0.8.dist-info/RECORD
