Metadata-Version: 2.4
Name: clickup-mcp-server
Version: 0.0.8
Summary: 🦾 A strong MCP server for ClickUp.
Project-URL: Homepage, https://github.com/Chisanan232/clickup-mcp-server
Project-URL: Repository, https://github.com/Chisanan232/clickup-mcp-server
Project-URL: Documentation, https://chisanan232.github.io/clickup-mcp-server/
Project-URL: Changelog, https://chisanan232.github.io/clickup-mcp-server/docs/next/changelog
Project-URL: Project Management, https://app.clickup.com/9018752317/v/f/90185744050/90184991515
Author-email: Chisanan232 <chi10211201@cycu.org.tw>
License: 
License-File: LICENSE
Keywords: clickup,clickup-mcp,clickup-mcp-server,mcp,mcp-server
Classifier: Development Status :: 3 - Alpha
Classifier: Intended Audience :: Developers
Classifier: License :: OSI Approved :: MIT License
Classifier: Operating System :: OS Independent
Classifier: Programming Language :: Python :: 3
Classifier: Programming Language :: Python :: 3.13
Classifier: Topic :: Software Development :: Libraries :: Python Modules
Classifier: Topic :: Utilities
Requires-Python: >=3.13
Requires-Dist: fastapi>=0.116.0
Requires-Dist: httpx>=0.27.0
Requires-Dist: mcp[cli]>=1.10.1
Requires-Dist: pydantic>=2.11.7
Requires-Dist: python-dotenv>=1.0.0
Requires-Dist: uvicorn>=0.35.0
